quillpy/__init__.py
quillpy/__main__.py
quillpy/quill.py
quillpy-0.2.7.dist-info/licenses/LICENCE
quillpy-0.2.7.dist-info/METADATA
quillpy-0.2.7.dist-info/WHEEL
quillpy-0.2.7.dist-info/entry_points.txt
quillpy-0.2.7.dist-info/top_level.txt
quillpy-0.2.7.dist-info/RECORD
